Workbook
Name aportes: ferramenta_Pink.Invest!$D$17
Name div_mens: ferramenta_Pink.Invest!$D$21
Name patrim_ac: ferramenta_Pink.Invest!$D$20
Name Rendimento_carteira: ferramenta_Pink.Invest!$D$12
Name salario: ferramenta_Pink.Invest!$D$11
Name sugestao.Invest: ferramenta_Pink.Invest!$D$13
Name taxa: ferramenta_Pink.Invest!$D$19
Name tempo: ferramenta_Pink.Invest!$D$18

Sheet ferramenta_Pink.Invest
B10: CONFIGURAÇÕES
B11: Salário | D11: 1000
B12: Rendimento carteira | D12: 0.01
B13: sugestão de Investimento (30%) | D13: =D11*30% -> 300
B16: Investimento Mensal
B17: Quanto Investir Por mês? | D17: 300
B18: Por quantos anos? | D18: 6
B19: Taxa de rendimento Mensal? | D19: 0.01079
B20: Patrimônio Acumulado? | D20: =FV(taxa,tempo*12,aportes*-1) -> 32409.06
B21: Dividendos mensais? | D21: =patrim_ac*Rendimento_carteira -> 324.0906
B23: Cenários | D23: Dividendos
A24: 2 | B24: Quanto em 2 anos? | C24: =FV($D$19,$A24*12,$D$17*-1) -> 8168.2882 | D24: =C24*Rendimento_carteira -> 81.682882
A25: 5 | B25: Quanto em 5 anos? | C25: =FV($D$19,$A25*12,$D$17*-1) -> 25133.074 | D25: =C25*Rendimento_carteira -> 251.33074
A26: 10 | B26: Quanto em 10 anos? | C26: =FV($D$19,$A26*12,$D$17*-1) -> 72985.264 | D26: =C26*Rendimento_carteira -> 729.85264
A27: 20 | B27: Quanto em 20 anos? | C27: =FV($D$19,$A27*12,$D$17*-1) -> 337559.52 | D27: =C27*Rendimento_carteira -> 3375.5952
A28: 30 | B28: Quanto em 30 anos? | C28: =FV($D$19,$A28*12,$D$17*-1) -> 1296650.9 | D28: =C28*Rendimento_carteira -> 12966.509
B31: Perfil | C31: Agressivo
B32: Valor a ser investido ao mês | C32: 600
B34: Tipos de FII | C34: Percentual sugerido | D34: Valores
B35: Papel | C35: =VLOOKUP($C$31&"-"&B35,Planilha2!$C:$F,4,) -> 0.5 | D35: =C35*$C$32 -> 300
B36: Tijolo | C36: =VLOOKUP($C$31&"-"&B36,Planilha2!$C:$F,4,) -> 0.1 | D36: =C36*$C$32 -> 60
B37: Híbridos | C37: =VLOOKUP($C$31&"-"&B37,Planilha2!$C:$F,4,) -> 0.05 | D37: =C37*$C$32 -> 30
B38: FOFs | C38: =VLOOKUP($C$31&"-"&B38,Planilha2!$C:$F,4,) -> 0.05 | D38: =C38*$C$32 -> 30
B39: Desenvolvimento | C39: =VLOOKUP($C$31&"-"&B39,Planilha2!$C:$F,4,) -> 0.2 | D39: =C39*$C$32 -> 120
B40: Hotelarias | C40: =VLOOKUP($C$31&"-"&B40,Planilha2!$C:$F,4,) -> 0.1 | D40: =C40*$C$32 -> 60
D41: =SUM(D35:D40) -> 600

Sheet Planilha2
C6: chave | D6: perfil | E6: Tipos de FII | F6: %
C7: =D7&"-"&E7 -> Conservador-Papel | D7: Conservador | E7: Papel | F7: 0.3
C8: =D8&"-"&E8 -> Conservador-Tijolo | D8: Conservador | E8: Tijolo | F8: 0.5
C9: =D9&"-"&E9 -> Conservador-Híbridos | D9: Conservador | E9: Híbridos | F9: 0.1
C10: =D10&"-"&E10 -> Conservador-FOFs | D10: Conservador | E10: FOFs | F10: 0.1
C11: =D11&"-"&E11 -> Conservador-Desenvolvimento | D11: Conservador | E11: Desenvolvimento | F11: 0
C12: =D12&"-"&E12 -> Conservador-Hotelarias | D12: Conservador | E12: Hotelarias | F12: 0
C13: =D13&"-"&E13 -> moderado-Papel | D13: moderado | E13: Papel | F13: 0.32
C14: =D14&"-"&E14 -> moderado-Tijolo | D14: moderado | E14: Tijolo | F14: 0.4
C15: =D15&"-"&E15 -> moderado-Híbridos | D15: moderado | E15: Híbridos | F15: 0.08
C16: =D16&"-"&E16 -> moderado-FOFs | D16: moderado | E16: FOFs | F16: 0.1
C17: =D17&"-"&E17 -> moderado-Desenvolvimento | D17: moderado | E17: Desenvolvimento | F17: 0.1
C18: =D18&"-"&E18 -> moderado-Hotelarias | D18: moderado | E18: Hotelarias | F18: 0.1
... C24: =D24&"-"&E24 -> Agressivo-Hotelarias | D24: Agressivo | E24: Hotelarias | F24: 0.1
